{"contract":"KT1RJ6PbjHpwc3M5rw5s2Nbmefwbuwbdxton","network":"mainnet","level":1454369,"token_id":59409,"symbol":"OBJKT","name":"Synthetic Brazil - Carnaval","decimals":0,"description":"Synthetic media illustrating some aspects of Brazil | 4096x2160px | Created by @sandromiccoli using aphantasia by @eps696","artifact_uri":"ipfs://QmTkm12pkjVB3hgDecXnrR5nuWFyGem2PKo4X1PoPEL2vq","thumbnail_uri":"ipfs://QmNrhZHUaEqxhyLfqoq1mtHSipkWHeT31LNHb1QEbDHgnc","is_transferable":true,"creators":["tz1Q4r6CMMNRvvQBZUFU5za4aTFZpC43rX8G"],"tags":["SyntheticMedia","CLIP","NeuralNetworks","Aphantasia","GenerativeArt","Generative","ArtificialIntelligence","MachineLearning","AI","ML","AIArt","MLArt","NeuralArt"],"formats":[{"mimeType":"image/jpeg","uri":"ipfs://QmTkm12pkjVB3hgDecXnrR5nuWFyGem2PKo4X1PoPEL2vq"}],"token_info":{"@@empty":"ipfs://QmSv97pBc5Mwy9hNd8ozUFEwpf1Hrheojdw4FgK7v9eCwP"},"supply":"10","transfered":8}