{"__version": 1, "token_id": 171726, "symbol": "OBJKT", "name": "Pink symmetrical Stair Tunnel", "description": "I am interested in symmetrical stairs and I try to reconstruct these stairs in 3d space due to the fact that it is difficult to photograph symmetrical stairs.( Resolution 1920x1080 )", "artifact_uri": "ipfs://QmdsZzHu7HFVxyX25FKKyTPQu331b2adhMQxX9MwmXyD8D", "display_uri": "ipfs://QmcGB1Ho5i2zbYzpHRgs4U4Z1HzA39fCo9CrqgbSGi6UxY", "thumbnail_uri": "ipfs://QmNrhZHUaEqxhyLfqoq1mtHSipkWHeT31LNHb1QEbDHgnc", "formats": [{"uri": "ipfs://QmdsZzHu7HFVxyX25FKKyTPQu331b2adhMQxX9MwmXyD8D", "mimeType": "video/mp4"}], "creators": ["tz1VLZx1e2xFgZG6ayXA7PT5LgHnLaDsbBGb"], "tags": ["MORTEZAYOUSEFI", "ARTWORK", "3D", "TEZOS", "HICETNUNC", "STAIR", "NFT", "3DART", "DIGITALART", "TUNNEL", "ART"], "extra": {}}