{"__version": 1, "token_id": 189126, "symbol": "OBJKT", "name": "New Manila", "description": "A cyberpunk city based on New Manila, inspired by an actual location of the same name. Procedurally generated using Voronoi textures, noise textures, and JSPlacement with added holograms and traffic. Rendered in Blender Eevee. Featured OBJKT: #167935 \"amalgamation_006\" by @GrotesqueChiq. By Lucius Felimus: https://www.luciusfelimus.com/\n", "artifact_uri": "ipfs://Qma7fNobDqeCTyWii71ANDBiSPyieK8AZJEB8Ysxbz6fCy", "display_uri": "ipfs://QmQKnRvFtNNwbxEtC438X8XnjMxvZFpWZFLxQTtA6mTvxK", "thumbnail_uri": "ipfs://QmNrhZHUaEqxhyLfqoq1mtHSipkWHeT31LNHb1QEbDHgnc", "formats": [{"uri": "ipfs://Qma7fNobDqeCTyWii71ANDBiSPyieK8AZJEB8Ysxbz6fCy", "mimeType": "image/png"}], "creators": ["tz1VBwBKcn87qLbMs1csbcbTtJuodefmfMDH"], "tags": ["cyberpunk", "futuristic", "scifi", "city", "neon", "manila", "philippines", "digital", "blender", "render", "3d", "generative"], "extra": {}}