{"__version": 1, "token_id": 249195, "symbol": "OBJKT", "name": "Floating points resonating vortex", "description": "geometric figures resonating,frequency and oscilloscope revealing natural beauties visions\" \nPSILOSCOPE  is a psilosamples series of jams experiences with soundwaves and Lo-Fi oscilloscopes", "artifact_uri": "ipfs://QmYjns1Bn3WK3tjq11WfU1SeojiYvkNHgjvo4empeBrZtm", "display_uri": "ipfs://Qmcjgcx4pZpDRkCsQAJZ1wUtgJq2uKgpvosWw6YLmrTaEd", "thumbnail_uri": "ipfs://QmNrhZHUaEqxhyLfqoq1mtHSipkWHeT31LNHb1QEbDHgnc", "formats": [{"uri": "ipfs://QmYjns1Bn3WK3tjq11WfU1SeojiYvkNHgjvo4empeBrZtm", "mimeType": "video/mp4"}], "creators": ["tz1bTYhe71BQeY7Z42gsvEp52dvtkPHA5tCF"], "tags": ["psilosamples", "chaos", "oscilloscope", "geometry"], "extra": {}}