{"contract": "KT1RJ6PbjHpwc3M5rw5s2Nbmefwbuwbdxton", "network": "mainnet", "level": 1495182, "token_id": 107083, "symbol": "OBJKT", "name": "ERROR_226", "decimals": 0, "description": "this piece is part of my ERROR series. after years of creating art that pleases the masses, i felt burned out. i hated every piece i created. ERROR was my art renaissance. every painting was created without an expectation. i start each of them without looking at it and afterwards let my mind decide what it sees in the shapes. but these are not only reflections of my mind. what do you see?", "artifact_uri": "ipfs://QmUGH1hp5uMCMyxS9cjA1kFdLMJ4UenQU9tkxG8a3ZWfkg", "display_uri": "ipfs://QmQp1mRs8SnxeDdQPstppCrApLYVRER4NxiKeVo2vGEaEG", "thumbnail_uri": "ipfs://QmNrhZHUaEqxhyLfqoq1mtHSipkWHeT31LNHb1QEbDHgnc", "is_transferable": true, "creators": ["tz1Nwf33AvCZic6kKEB2Fe1czDLXHTZFDM67"], "tags": ["dark", "horror", "art", "illustration", "painting", "b&w", "dirty", "abstract", "creepy", "death", "weird", "strange"], "formats": [{"mimeType": "video/mp4", "uri": "ipfs://QmUGH1hp5uMCMyxS9cjA1kFdLMJ4UenQU9tkxG8a3ZWfkg"}], "token_info": {"@@empty": "ipfs://QmRHHsvrrEpyN7wbmDKxham5mcmKz8kEgKgkQHZveGmyQX"}, "supply": "5", "transfered": 0}