{"__version":1,"extra":{"display_uris":[]},"token_id":61583,"symbol":"OBJKT","creators":["tz1h4wE8yjKohJn6PmAJVnf2r3MLXrLTESw1"],"name":"Hickey Punks #88 | Mystique","description":"Hickey Punks have been naughty. There will be 100 unique 1 of 1 Hickey Punks total. Hickey Punks are created by @clipdad_","tags":["protector","of","all","mutants","mystique","clipdad","hickey","punks"],"formats":[{"mimeType":"image/jpeg","uri":"ipfs://QmRC2pt12xPWEYpQ8xiwnvs9D4TY1xwoLLfUvXrinz67nv"}],"artifact_uri":"ipfs://QmRC2pt12xPWEYpQ8xiwnvs9D4TY1xwoLLfUvXrinz67nv","display_uri":"","thumbnail_uri":"ipfs://QmNrhZHUaEqxhyLfqoq1mtHSipkWHeT31LNHb1QEbDHgnc"}