{"__version": 1, "token_id": 222007, "symbol": "OBJKT", "name": "Escorted to Runersia", "description": "(Second piece in the Isekai Taxi series)\n(Wear your headphones for maximum experience)\u2028\u2028\n\nA scene where each taxi entering the isekai would get escorted to \u201cRunersia\u201d by a celestial giant orb. What could be waiting there?\n\nAs the both world collide, the humans of earth are still slightly visible in the horizon.\n\n2160x2160 seamless looping MP4 with BGM", "artifact_uri": "ipfs://QmSq2frmYtu93PxMgzEfPf2cutYHeDa3Yzkh3PPLTixFdo", "display_uri": "ipfs://QmdBHs7ssWBzAFMkTxYbWTyvxHF5CeKyrRFqi4AW1nfa2k", "thumbnail_uri": "ipfs://QmNrhZHUaEqxhyLfqoq1mtHSipkWHeT31LNHb1QEbDHgnc", "formats": [{"uri": "ipfs://QmSq2frmYtu93PxMgzEfPf2cutYHeDa3Yzkh3PPLTixFdo", "mimeType": "video/mp4"}], "creators": ["tz2UYLKTisJDAqAXTCn2u3EzMDHYMBr9JVb5"], "tags": ["pictorial", "parallax", "3D", "streetphotography", "japan", "taxi", "isekai", "indiedo", "loop"], "extra": {}}