{"__version":1,"extra":{"display_uris":[]},"token_id":93856,"symbol":"OBJKT","creators":["tz1Sqik646RmWuuuHbvkf8Uykg8iKMkBTx5Y"],"name":"Micro Tile #15","description":"800x800 px | 20 fps | 200 frame | 14,6 mb | by @zatelliti Micro Tile is a collection of 100 generated geometries divided in 10 set, each containing 10 artworks, edition of 10.","tags":["microtile","proceduralart","mathnodes"],"formats":[{"mimeType":"image/gif","uri":"ipfs://QmZXB79Bje8VW4ZBVQJKCvg1rSUqmV1GhURCArL51J3L5G"}],"artifact_uri":"ipfs://QmZXB79Bje8VW4ZBVQJKCvg1rSUqmV1GhURCArL51J3L5G","display_uri":"","thumbnail_uri":"ipfs://QmNrhZHUaEqxhyLfqoq1mtHSipkWHeT31LNHb1QEbDHgnc"}