{"contract":"KT1RJ6PbjHpwc3M5rw5s2Nbmefwbuwbdxton","network":"mainnet","level":1449969,"token_id":54676,"symbol":"OBJKT","name":"The Ether Blaster","decimals":0,"description":"[PT/BR]Tava esperando o que? uma arminha com neon que saiu direto de ciberpunk? se sim, você tem pouca cultura ficcional,\"pew...pew....BOOM\" [ENG]What were you waiting for? a little gun with neon that comes straight out of cyberpunk? if yes you have a little fictional culture, \"pew...pew....BOOM\"","artifact_uri":"ipfs://QmPfVMJnnrBw9S17oxFz8P8vwzsjgaW8dKxDoVbHokHbP7","thumbnail_uri":"ipfs://QmNrhZHUaEqxhyLfqoq1mtHSipkWHeT31LNHb1QEbDHgnc","creators":["tz1VvibQd1hhvQ2G4NzvgDRQMv9fBtGkuW1F"],"tags":["#crypto","#lasergun","#rpg","#futurist","#spaceweapon","#weapon","#future","#card","#cardgame","#coinlaser","#pixel","#pixelart","#3d","#destruction","#gun","#coinexplosion","#Ethereum","#laser","#coinpower","#cryptocoin","#brazilart"],"formats":[{"mimeType":"image/gif","uri":"ipfs://QmPfVMJnnrBw9S17oxFz8P8vwzsjgaW8dKxDoVbHokHbP7"}],"token_info":{"@@empty":"ipfs://QmdUaMYUsaBsBdfLH2KDXxR3Sg6iVhHnzCQBhmvgrLzrtu"},"supply":"16","transfered":21}