{"__version":1,"extra":{"display_uris":[]},"token_id":87776,"symbol":"OBJKT","creators":["tz1NUKVdKfE9ESUKxeG5fVaGZGgf8bd1DU2U"],"name":"Endless flight #17","description":"A delicate butterfly preserved forever flitting around the blockchain. Check out instagram @wonderroom.studio for more info on the collection","tags":["butterfly","animal","nature","animation"],"formats":[{"mimeType":"image/gif","uri":"ipfs://QmPaz14Kqbq4AinUehDyfQkNk2X2tCke4A9aZrKh78GXiK"}],"artifact_uri":"ipfs://QmPaz14Kqbq4AinUehDyfQkNk2X2tCke4A9aZrKh78GXiK","display_uri":"","thumbnail_uri":"ipfs://QmNrhZHUaEqxhyLfqoq1mtHSipkWHeT31LNHb1QEbDHgnc"}