{"contract":"KT1RJ6PbjHpwc3M5rw5s2Nbmefwbuwbdxton","network":"mainnet","level":1403433,"token_id":15030,"symbol":"OBJKT","name":"AV_05","decimals":0,"description":"Automaton Variations 05 - Umanesimo Artificiale - Automaton Variations is an audiovisual album by the sound artist and experimental composer @vvaxx_ and the visual artist @ba.ransu. Minimalist in its aesthetic and rigorous in its approach, the album celebrates the creativity in coding and elevates computer programming as an artistic expression. (hic et nunc exclusive)","artifact_uri":"ipfs://QmSTc7wXzQWA2KmMvnvV5RXnCVkiS2sMszEVJgXSBoxT3W","thumbnail_uri":"ipfs://QmNrhZHUaEqxhyLfqoq1mtHSipkWHeT31LNHb1QEbDHgnc","formats":[{"mimeType":"video/quicktime","uri":"ipfs://QmSTc7wXzQWA2KmMvnvV5RXnCVkiS2sMszEVJgXSBoxT3W"}],"token_info":{"@@empty":"ipfs://Qme7bveshDGpJGYQo44cmqWCWL7aQ31soPpDxyyHVrdJj4"},"supply":"1","transfered":1}