{"__version": 1, "token_id": 133973, "symbol": "OBJKT", "name": "ERR0R1", "description": "smol cmd prompt (for smol messages) keeps glitching on reboot / 10x7px animated GIF command prompt series - season 1 finale / @bernizeck", "artifact_uri": "ipfs://QmaZfiiBuYYVBBxC1GDEoUcEmvgPaxMNEUpGB4Aiwgi3Jn", "display_uri": "ipfs://QmaZfiiBuYYVBBxC1GDEoUcEmvgPaxMNEUpGB4Aiwgi3Jn", "thumbnail_uri": "ipfs://QmNrhZHUaEqxhyLfqoq1mtHSipkWHeT31LNHb1QEbDHgnc", "formats": [{"uri": "ipfs://QmaZfiiBuYYVBBxC1GDEoUcEmvgPaxMNEUpGB4Aiwgi3Jn", "mimeType": "image/gif"}], "creators": ["tz1PYVjdNTcb7i3vGjf3G2eKzG91rKyYmhGp"], "tags": ["smol", "smolgang", "smolnft", "pixel", "pixelart", "commandprompt", "prompt", "screen", "glitch", "glitchart", "window", "gif", "animated", "loop", "10x7"], "extra": {}}