{"__version": 1, "token_id": 161931, "symbol": "OBJKT", "name": "Polychromatics 1.1", "description": "Polychromatics consists of a series of images in which light and form are rendered with discrete vector graphic shapes. The resulting image elements and layered and composited to produce a fluid interaction of color. Subtle variation occurs each time the work is accessed.", "artifact_uri": "ipfs://QmbAwRdH8ZohSTe3SNhDNTRif83YtwDn9v35WDJ5w8qUZT", "display_uri": "ipfs://QmTPW9tJStpGQDhQzFoVzEvj5DrpcaoyZUGj4xovV3cpBh", "thumbnail_uri": "ipfs://QmYrZtdmUmrnBY5KTYtnyuJcbtGC3nmKPkBtiqQBwAAqAP", "formats": [{"uri": "ipfs://QmbAwRdH8ZohSTe3SNhDNTRif83YtwDn9v35WDJ5w8qUZT", "mimeType": "application/x-directory"}], "creators": ["tz1M348mq4NQsN56yGhFtLo66LDRHD9WjHSu"], "tags": ["color", "vector", "canvas", "abstract"], "extra": {}}