{"__version": 1, "token_id": 210331, "symbol": "OBJKT", "name": "Nanobots Eat the Sky", "description": "p5js with a painted star scene png as background.\n\nRandom walker nanobots both breed and paint over the background.\n\nAs each new nanobot is born, they are assigned a random color either from a set of 'organic' tones of red (#522529), yellow (#fbd17e), green (#436c3d), blue (#145879), white or black.\n\nThe nanobots will eventually fill the screen although this will take time as they swarm in one spot and do stop breeding once their population reaches 5000.", "artifact_uri": "ipfs://QmXz3jYiehTAprJnUFS7CgMSJtL43hPEzk4SRuACanF1m3", "display_uri": "ipfs://Qmd69P7bajthnm8NHC8gLJFUdDmD7YMS5rGnegrggonV1y", "thumbnail_uri": "ipfs://QmWp9Yd68UYAbSkMX2XvCffA8MiAeHVaP1fJKxPd3PYess", "formats": [{"uri": "ipfs://QmXz3jYiehTAprJnUFS7CgMSJtL43hPEzk4SRuACanF1m3", "mimeType": "application/x-directory"}], "creators": ["tz1iejkdRYyq7WdVtrXgpq1dtazsGpthkF1U"], "tags": ["generativeart", "javascript", "p5.js", "digitalexpressionism", "expressionism"], "extra": {}}