{"__version":1,"extra":{"display_uris":[]},"token_id":86053,"symbol":"OBJKT","creators":["tz1f4pgkAbNvw1Et3sU9p2YBK4nwZU38ceG1"],"name":"游놓游놓游놓battle for Cydonia!游놓游놓游놓","description":"my source of inspiration for this collection was the movie Prometheus","tags":["muse","Prometheus","alien","spoce.spaceship","afterearth","apocalypse","cydonia","collage"],"formats":[{"mimeType":"video/mp4","uri":"ipfs://QmZ7mM7r816vjcgB1xBUAPnfeNyGopcyjdq6Ya2LUDvBo6"}],"artifact_uri":"ipfs://QmZ7mM7r816vjcgB1xBUAPnfeNyGopcyjdq6Ya2LUDvBo6","display_uri":"","thumbnail_uri":"ipfs://QmNrhZHUaEqxhyLfqoq1mtHSipkWHeT31LNHb1QEbDHgnc"}