{"__version":1,"extra":{"display_uris":[]},"token_id":123966,"symbol":"OBJKT","creators":["tz1LUqguDivxgbi6d94AuwDfoF2MtS5Mb9p9"],"name":"A few miles south","description":"Illustration by @iamnotwal","tags":["@iamnotwal","notwal","wal","illustration","jpg","2160x2160px","72ppi","bright","fun","colorful","balloon","air-balloon","woman","reading","relaxing","city","building","chimney","roof","man","hanging","sky","blue","red","yellow","green","primary",""],"formats":[{"uri":"ipfs://QmYPq64PgAjXohZRECfz4WaBhChZ3jwsVowcXoDhPN7tXH","mimeType":"image/jpeg"}],"artifact_uri":"ipfs://QmYPq64PgAjXohZRECfz4WaBhChZ3jwsVowcXoDhPN7tXH","display_uri":"ipfs://QmQZWArWXYNUkD28tBnTCXegB9VXdHH7M7qQvctehun2Dd","thumbnail_uri":"ipfs://QmNrhZHUaEqxhyLfqoq1mtHSipkWHeT31LNHb1QEbDHgnc"}