{"__version":1,"extra":{"display_uris":[]},"token_id":60366,"symbol":"OBJKT","creators":["tz1auyGWVy1DYKFc9MKkRZRUZxcRz8DkMRgf"],"name":"OCEANIC SIGNAL (Still Image Ver.) 1/3","description":"Resolution:720x284.The Still Image is from my AudioVisual work, OCEANIC SIGNAL, 2007.  more detail : http://www.yaolouk.com/works/os.html.","tags":["ink","audiovisual"],"formats":[{"mimeType":"image/jpeg","uri":"ipfs://QmdxtcdGVnXeuoHWdk6Ur8r6ThBjhUwvC8HgTgQvmQmSfc"}],"artifact_uri":"ipfs://QmdxtcdGVnXeuoHWdk6Ur8r6ThBjhUwvC8HgTgQvmQmSfc","display_uri":"","thumbnail_uri":"ipfs://QmNrhZHUaEqxhyLfqoq1mtHSipkWHeT31LNHb1QEbDHgnc"}