{"__version": 1, "token_id": 179055, "symbol": "OBJKT", "name": "Black and Gold", "description": "A star is born, shrouded in a cloak of black and gold. Adam's 7th work in a series exploring abstract compositions using GAN apps and digital painting techniques. https://twitter.com/AdamFryda\n", "artifact_uri": "ipfs://QmcEytQxv2mswM7yvNsZtGxTT7VcirwSQmLfFr4zGbfbwQ", "display_uri": "ipfs://QmeQSLrGvD13bqRvBhBNuqQNNRtkSFxSgirVjWkX7qHSNJ", "thumbnail_uri": "ipfs://QmNrhZHUaEqxhyLfqoq1mtHSipkWHeT31LNHb1QEbDHgnc", "formats": [{"uri": "ipfs://QmcEytQxv2mswM7yvNsZtGxTT7VcirwSQmLfFr4zGbfbwQ", "mimeType": "image/jpeg"}], "creators": ["tz1To8LSYnYrhkuMwFpLneJR9HamgL9skuYp"], "tags": ["Digitalart", "GAN", "Digitalpainting", "Abstract", "2D", "Static", "Space", ""], "extra": {}}