{"__version":1,"extra":{"display_uris":[]},"token_id":103729,"symbol":"OBJKT","creators":["tz1Z9AUVhrNZ7tF4z2U4aMWxKmgcxv7CBiPJ"],"name":"Space Between Us","description":"There is space between us. Between you and I. Us and them. Them amongst themselves. I wonder why... Watching the earth from up here. I see too much space, not enough of us. Too much bickering, too much fighting, too many wars. Not enough of us. Wars can outnumber us. When will we ever realize, we are the same species? and we are fighting a war that cannot be won. ","tags":["hiceturco","space","between","astronaut","time","forgive","forget","nomore","gone","blendreams","world","earth","alone","together","away","why","vast"],"formats":[{"mimeType":"image/png","uri":"ipfs://QmQAM1zMpxUgNGDgAVd1keqfsZKD97SL74FL3HUqKVxfBF"}],"artifact_uri":"ipfs://QmQAM1zMpxUgNGDgAVd1keqfsZKD97SL74FL3HUqKVxfBF","display_uri":"ipfs://QmZ3epnBezV2zqVdyHZvpFaaoMHCpNRfj97goVvfyWcm8T","thumbnail_uri":"ipfs://QmNrhZHUaEqxhyLfqoq1mtHSipkWHeT31LNHb1QEbDHgnc"}