{"__version":1,"extra":{"display_uris":[]},"token_id":59901,"symbol":"OBJKT","creators":["tz1YvJvemXC2tGoHNMizpJTLpMDsUrKbhwVY"],"name":"Fulfilling","description":"Fulfilled people know where they want to go in life, and they know how to get there. Not only that, but they're not bogged down in hopelessness that it'll never happen. They're full of hope for the future and optimistic that with hard work and prayer, they'll see their plans become reality.","tags":["abstract","unique","fractal","glow","particles"],"formats":[{"mimeType":"video/mp4","uri":"ipfs://Qmegicq7ewXRZCGKn44x5JuzYyyMM6jubxt47jWda9ohsD"}],"artifact_uri":"ipfs://Qmegicq7ewXRZCGKn44x5JuzYyyMM6jubxt47jWda9ohsD","display_uri":"","thumbnail_uri":"ipfs://QmNrhZHUaEqxhyLfqoq1mtHSipkWHeT31LNHb1QEbDHgnc"}