{"__version":1,"extra":{"display_uris":[]},"token_id":93835,"symbol":"OBJKT","creators":["tz1MTJiAUnY3WmkLUHyZufe3zbp2wnvv7w19"],"name":"Garden Of Love","description":"*sound on* A stroll through the garden of love to meet with unexpected omens, overlaid with bees. Elysium Perdita - Animated from the still life painting by Frans Snyders c. 1630 - Poem by William Blake - Produced and performed by Laurence Fuller @laurencefuler","tags":["Laurence","Fuller","William","Blake"],"formats":[{"mimeType":"video/mp4","uri":"ipfs://QmYT21GCHrcTM8XMYcu7ccoohTnhivuh9bkmPDqJva86cc"}],"artifact_uri":"ipfs://QmYT21GCHrcTM8XMYcu7ccoohTnhivuh9bkmPDqJva86cc","display_uri":"","thumbnail_uri":"ipfs://QmNrhZHUaEqxhyLfqoq1mtHSipkWHeT31LNHb1QEbDHgnc"}