{"__version":1,"extra":{"display_uris":[]},"token_id":104858,"symbol":"OBJKT","creators":["tz1Kz7fCjjFh83yQFrZTCYLhzpMwpJAK5fqD"],"name":"0020AI","description":"Artificial intelligence unites with human creativity. 0000AI is a digital art series that explores new ways of creating art by combining generative adversarial networks with human vision.","tags":["0000AI","ai","artificialintelligence","digitalart","digitalpainting","generativeart","gan","neuralnetwork","surreal","surrealism","abstract","abstractart","digitalpainting","art","typography","E"],"formats":[{"mimeType":"image/jpeg","uri":"ipfs://QmetExwbebB8mpxKj4fCGjmEqC2izvuBkMbWZ8pKu4MBwW"}],"artifact_uri":"ipfs://QmetExwbebB8mpxKj4fCGjmEqC2izvuBkMbWZ8pKu4MBwW","display_uri":"ipfs://QmVyDq2GJRkHNaywgFNmrxfhQbjE8w39524K9qkQPFFypK","thumbnail_uri":"ipfs://QmNrhZHUaEqxhyLfqoq1mtHSipkWHeT31LNHb1QEbDHgnc"}