{"__version":1,"extra":{"display_uris":[]},"token_id":62389,"symbol":"OBJKT","creators":["tz1PgueFeqHU1nN8UzpsN48RSzKXHuMBTLB8"],"name":"Soup","description":"Slightly autobiographical, story of a very bad day (pen on paper with digital color)","tags":["drawing","painting","digitalpainting","illustration","robot","pot","fun","humor","digitalart"],"formats":[{"mimeType":"image/png","uri":"ipfs://QmW466DeAYBAgDQMZNBQgQqxMCp7r7fh5wN43GPL76uhos"}],"artifact_uri":"ipfs://QmW466DeAYBAgDQMZNBQgQqxMCp7r7fh5wN43GPL76uhos","display_uri":"","thumbnail_uri":"ipfs://QmNrhZHUaEqxhyLfqoq1mtHSipkWHeT31LNHb1QEbDHgnc"}