{"__version": 1, "token_id": 233188, "symbol": "OBJKT", "name": "Premonition", "description": "Sometimes we are overwhelmed by an inexplicable sense of anxiety, as if something is about to happen. in this picture I have reflected this feeling. If you look deeper, then it is not scary, but very strong and gradually covers you completely.", "artifact_uri": "ipfs://QmRpbNUE61d5MYJdsgAuQhpFDgCySmX4t1SKwhwopFS6Uu", "display_uri": "ipfs://Qmf7Q2UQzD8YZj5WhMBkWNMXxyJ9DKSNHzZWjqxYZeVKaV", "thumbnail_uri": "ipfs://QmNrhZHUaEqxhyLfqoq1mtHSipkWHeT31LNHb1QEbDHgnc", "formats": [{"uri": "ipfs://QmRpbNUE61d5MYJdsgAuQhpFDgCySmX4t1SKwhwopFS6Uu", "mimeType": "video/mp4"}], "creators": ["tz1fpPvUAer85jP79SXY7UZCGYugaDzKnzVW"], "tags": ["feeling", "animation", "emotion", "trippy", "anxiety", "Premonition", "survival", "dragon", "gif", "emotion", "wolf", "nightmare", "newnft", "rare", "doodleart", "drawing", "dark", "psychedelic", "esoteric"], "extra": {}}