{"contract":"KT1RJ6PbjHpwc3M5rw5s2Nbmefwbuwbdxton","network":"mainnet","level":1399461,"token_id":12476,"symbol":"OBJKT","name":"remixing invisible dots inside a fine coconut","decimals":0,"description":"pls fact... do you hear it ? I hear the leaves of the trees outside my window hustling to the winds blowing in all directions. they sound like a giant crowd clapping their hands from a very far space. change is coming from all directions towards some strange unpredictable path. on a cycle of birth and death, destruction and creation. -my pet rock, orange || ooakosimo","artifact_uri":"ipfs://QmZwNHDaP58zBLEgCVkXe8aSypRNWi6B6oQH4VbvB11ZMz","thumbnail_uri":"ipfs://QmNrhZHUaEqxhyLfqoq1mtHSipkWHeT31LNHb1QEbDHgnc","formats":[{"mimeType":"image/gif","uri":"ipfs://QmZwNHDaP58zBLEgCVkXe8aSypRNWi6B6oQH4VbvB11ZMz"}],"token_info":{"@@empty":"ipfs://QmZ7rNozwPTK7qLvP2Y3rBRED6eWYzEfXCMwUcC4G6pFLJ"},"supply":"11","transfered":23}