{"contract":"KT1RJ6PbjHpwc3M5rw5s2Nbmefwbuwbdxton","network":"mainnet","level":1432634,"token_id":36306,"symbol":"OBJKT","name":"001 (America) B-Rank 2021","decimals":0,"description":"Animated gif containing all seven characters in B-Rank from 001 (America) OBJKT#29730. Classic video game imagery with every pixel replaced by a QR code linking to a tweet. The tweets embedded inside each video game character share one key word, the undisclosed title of that character. First exhibited at TedXLondon. (MDKtm.com/nft) 1000 X 800 pixels / 143 KB / 7 frame gif","artifact_uri":"ipfs://QmURjrK1ahvzunbkrcX8G8WFiSmQ3oGXKnvZ91JPHSFp7h","thumbnail_uri":"ipfs://QmNrhZHUaEqxhyLfqoq1mtHSipkWHeT31LNHb1QEbDHgnc","creators":["tz1LGghDbxz2FsnaHsSpU2N5jCqpEV8jAtNA"],"tags":["VIDEOGAMES","QRCODES","PIXELART","GRAPHICART","RETRO","1980S","@MDKTMNFT"],"formats":[{"mimeType":"image/gif","uri":"ipfs://QmURjrK1ahvzunbkrcX8G8WFiSmQ3oGXKnvZ91JPHSFp7h"}],"token_info":{"@@empty":"ipfs://QmZkx6soaSaoZvecs3Pqs3gdtXPrAGQZcK8UH9hNdUKrkE"},"supply":"20","transfered":54}