{"contract":"KT1RJ6PbjHpwc3M5rw5s2Nbmefwbuwbdxton","network":"mainnet","level":1444458,"token_id":48448,"symbol":"OBJKT","name":"Wall of Floppy Drives I","decimals":0,"description":"An homage to the wonders of the Floppy Disk. Back when Dad's mate from work was the single source of all my PC games - every one of them on at least 3 3.5\" floppy disks. Something that I think about occasionally while I email gigantic files from one household PC to the other when I can't be arsed to find a USB Key. Procedurally randomized to keep it fresh :: shig_nft 2021 ","artifact_uri":"ipfs://QmPjWDEs5a7n6DWENVcPVK2qC3mY462ru6GThz9hMZSAwJ","thumbnail_uri":"ipfs://QmNrhZHUaEqxhyLfqoq1mtHSipkWHeT31LNHb1QEbDHgnc","creators":["tz1QWFRpbN4rA8vABvxPAREtuffu6F1VKFTB"],"tags":["FloppyDisk","Voxel","ProceduralArt","Sh!g"],"formats":[{"mimeType":"image/svg+xml","uri":"ipfs://QmPjWDEs5a7n6DWENVcPVK2qC3mY462ru6GThz9hMZSAwJ"}],"token_info":{"@@empty":"ipfs://QmUxG7rGrV4fLc9kydkEPWjd6bfLQqsuDd6AuLk4ud99yA"},"supply":"20","transfered":58}