{"contract": "KT1RJ6PbjHpwc3M5rw5s2Nbmefwbuwbdxton", "network": "mainnet", "level": 1479226, "timestamp": "2021-05-20T05:00:06Z", "token_id": 89199, "symbol": "OBJKT", "name": "Light Suggestions // 1", "decimals": 0, "description": "Light Suggestions // 1 , May 2021, 2160x2160, Seamless 14 Second MP4 loop.  Collaboration with Sgt. Slaughtermelon\u2019s Chaos render patterns.  ", "artifact_uri": "ipfs://QmQMh5YgUwPxkHCLduNb26YMEhKkahQbCNHryrRTAMNHS4", "thumbnail_uri": "ipfs://QmNrhZHUaEqxhyLfqoq1mtHSipkWHeT31LNHb1QEbDHgnc", "is_transferable": true, "creators": ["tz1VdY7nbpBbNx1KuFJ5ubVVEa5pU2BAU5ge"], "tags": ["PATTERN", "OPART", "2021", "HSCOTTROTH", "PHOTOSHOP", "OP-ART", "GRADIENT", "ABSTRACT", "COLOR", ""], "formats": [{"mimeType": "video/mp4", "uri": "ipfs://QmQMh5YgUwPxkHCLduNb26YMEhKkahQbCNHryrRTAMNHS4"}], "token_info": {"@@empty": "ipfs://QmfVC9jCUafiDqx5TwiPGNjuyyZuDtNhx8vJ97rU2sUmc8"}, "supply": "6", "transfered": 3}