{"contract": "KT1RJ6PbjHpwc3M5rw5s2Nbmefwbuwbdxton", "network": "mainnet", "level": 1479453, "timestamp": "2021-05-20T08:49:06Z", "token_id": 89401, "symbol": "OBJKT", "name": "GREEN HEAVEN", "decimals": 0, "description": "This is my last letter To the afterworld I am on my way Let my voice be heard I have tried to be But it was not enough Oh, society, What have you done to us? What have you done to us? 3000 x 1688 px; 300 dpi; JPG;", "artifact_uri": "ipfs://QmZxUYkcjh4Yb3U3CKS45Z4SS5tkmYmmZktWGtgUdryhhG", "thumbnail_uri": "ipfs://QmNrhZHUaEqxhyLfqoq1mtHSipkWHeT31LNHb1QEbDHgnc", "is_transferable": true, "creators": ["tz1fHDP2PkDxwWi9i9aa5G4hkLe4iB64eNqb"], "tags": ["digital", "art", "illustration", "creepy", "pixel", "sort", "beeple", "anger", "heaven", "dirty", "space", "human", "android", "nude", "girl", ""], "formats": [{"mimeType": "image/jpeg", "uri": "ipfs://QmZxUYkcjh4Yb3U3CKS45Z4SS5tkmYmmZktWGtgUdryhhG"}], "token_info": {"@@empty": "ipfs://QmWVvc9SmSTLiAdVAz9hS16h66a9oYw7WkoRm6c4bHav4r"}, "supply": "1"}