{"contract":"KT1RJ6PbjHpwc3M5rw5s2Nbmefwbuwbdxton","network":"mainnet","level":1394208,"token_id":9524,"symbol":"OBJKT","name":"Northern Pole in real time","decimals":0,"description":"fork of Worldmap_northern.svg from Wikipedia to make it real time updating with current day and light set up. This is really a proof of concept. There are empiric approximation as it uses a circle with a fixed radius (don't support season).","artifact_uri":"ipfs://QmeQfKu7VWMzfWGF84Fnr1m5WVYe2ehq569LTRZqdCgUKg","thumbnail_uri":"ipfs://QmNrhZHUaEqxhyLfqoq1mtHSipkWHeT31LNHb1QEbDHgnc","formats":[{"mimeType":"image/svg+xml","uri":"ipfs://QmeQfKu7VWMzfWGF84Fnr1m5WVYe2ehq569LTRZqdCgUKg"}],"token_info":{"@@empty":"ipfs://Qme5YQbb4jsujxMmoNVAw64J5FQeVFGBtJmT2jUzQdpZag"},"supply":"1000","transfered":1002}