{"__version": 1, "token_id": 281621, "symbol": "OBJKT", "name": "Cotton Candy Kush JR", "description": "HIGH! I'm Cotton Candy Kush a Hybrid cannabis / marijuana strain. I'm having a great day aren't you? I just love candy, don't you? I love that shirt your wearing don't you like mine? I can tell we are going to be best friends, can't you?", "artifact_uri": "ipfs://bafybeic4veafbzktwbgj77vxmjhnfmmdlb6ei6r7eg34ser2zzv6srgaoe", "display_uri": "ipfs://bafybeifu54dhikzqm7zzdnrkjsowofu4azodb22ir7oxnaqfci264ibrpa", "thumbnail_uri": "ipfs://QmNrhZHUaEqxhyLfqoq1mtHSipkWHeT31LNHb1QEbDHgnc", "formats": [{"uri": "ipfs://bafybeic4veafbzktwbgj77vxmjhnfmmdlb6ei6r7eg34ser2zzv6srgaoe", "mimeType": "image/png"}], "creators": ["tz1VLKmYvcWL1xuisNc2xatHzqcLKopKC1JV"], "tags": ["blockchainbuds", "high", "nft", "blockchain", "babies", "fun", "thc", "hemp", "cannabis", "nftart", "blockchainbudbabies", "cute", "weed", "mmj", "pot", "marijuana", "hen100", "100hen"], "extra": {}}