{"__version": 1, "token_id": 177172, "symbol": "OBJKT", "name": "latent forests: 964cdd095c22", "description": "Latent walk video of a styleGAN model trained on the industrial forest landscapes of Western Canada. ", "artifact_uri": "ipfs://QmRRZSSo6AoF5EVcf2cpC1tCAsimXAijG3x9MNwTMiStQX", "display_uri": "ipfs://QmVyz3wKv6ZKwzcrzady2oEtkdk8WoiqLHfoNkHoKm6QSc", "thumbnail_uri": "ipfs://QmNrhZHUaEqxhyLfqoq1mtHSipkWHeT31LNHb1QEbDHgnc", "formats": [{"uri": "ipfs://QmRRZSSo6AoF5EVcf2cpC1tCAsimXAijG3x9MNwTMiStQX", "mimeType": "video/mp4"}], "creators": ["tz1QFk2DJhPkzp2nCN7Thpo4askJjQ3Zw6BU"], "tags": ["ffforests", "styleGAN", "industrial", "AI", "forests", "nature", "machine", "destruction", "forestry", "ML", "fabricatingfutureforests", "vincentcharlebois", "landscape", "forest", "silviculture", "machinelearning", "neuralnetworks", "GAN"], "extra": {}}