{"__version": 1, "token_id": 171462, "symbol": "OBJKT", "name": "Bloody Times - Dark", "description": "Generative and Glitch Art, made out of my original paintings and watercolors. Original and Unique artworks made by @HoracioMagnus, only 1/1 editions.", "artifact_uri": "ipfs://QmfPTuTeoJ7iY2zCNh1T1r3689u182JungCPxU6AuQqRiZ", "display_uri": "ipfs://QmfTQP6q1Nn3hZpSRDdxvBCgCwx3sAHGc2DyFYRy5g8SPa", "thumbnail_uri": "ipfs://QmNrhZHUaEqxhyLfqoq1mtHSipkWHeT31LNHb1QEbDHgnc", "formats": [{"uri": "ipfs://QmfPTuTeoJ7iY2zCNh1T1r3689u182JungCPxU6AuQqRiZ", "mimeType": "image/jpeg"}], "creators": ["tz1ahV5QihEU9eyo6fiJqdMrZuDiagxdJGXm"], "tags": ["generativeart", "digitalart", "glitch", "longterminvestment", "shorttermprofit", "@horaciomagnus", "unique", "art"], "extra": {}}