{"__version":1,"extra":{"display_uris":[]},"token_id":74462,"symbol":"OBJKT","creators":["tz1QpMCxND2BBPwjKpZaBfLZTqLKzEMKyGpj"],"name":"7B - Dunhill","description":"7B - Dunhill / Valor - R$10,00 / Nicotina - 0,7 / Pigarro - 35 / Estileira - 32 / Futum - 15 / Super Trago by Gabriel KOI / https://gabrielkoi.com/super-trago","tags":["SuperTNFT","SuperTrago","Collectible","GabrielKoi"],"formats":[{"mimeType":"model/gltf-binary","uri":"ipfs://QmRS21MinDyybc2mNSomnQWYF9kq8UewRUSbtEhKx2hiHt"}],"artifact_uri":"ipfs://QmRS21MinDyybc2mNSomnQWYF9kq8UewRUSbtEhKx2hiHt","display_uri":"","thumbnail_uri":"ipfs://QmNrhZHUaEqxhyLfqoq1mtHSipkWHeT31LNHb1QEbDHgnc"}