{"__version":1,"extra":{"display_uris":[]},"token_id":78760,"symbol":"OBJKT","creators":["tz1Pnnd7dtWUHhbJsYU7d38sLBy9juJC5816"],"name":"\"Porsche in the California Sunshine\"","description":"Photographed in California. Image size: 5200 x 5200 px. © 2021 MikeMDV. All Rights reserved.","tags":["Racing","Cars","Color","Photography","Neon","California","MikeMDV"],"formats":[{"mimeType":"image/jpeg","uri":"ipfs://QmTHFNRcLaFmVQK9aKqVqDQLwQrKbxn3ZNiRRzfVU2uSKk"}],"artifact_uri":"ipfs://QmTHFNRcLaFmVQK9aKqVqDQLwQrKbxn3ZNiRRzfVU2uSKk","display_uri":"","thumbnail_uri":"ipfs://QmNrhZHUaEqxhyLfqoq1mtHSipkWHeT31LNHb1QEbDHgnc"}