{"__version": 1, "token_id": 213814, "symbol": "OBJKT", "name": "Here and Now: Edition Two", "description": "Here and Now: Edition Two\nExperience created by Beets\nTicket Artwork by Shvembldr | 4000x4000 pixels| June 2021\nThis is your entry pass for the sold out Here and Now experience.\nhttps://wideawakeprojects.com/hereandnow/\n", "artifact_uri": "ipfs://QmY7p9UeGZeVUWRAfCQJm5nvQFHTNyfTWEPsH9Qympbkf1", "display_uri": "ipfs://QmRJXATxsS1nBo9tdHxpNWfQcEZ5teQohfaPgELusTzdNF", "thumbnail_uri": "ipfs://QmNrhZHUaEqxhyLfqoq1mtHSipkWHeT31LNHb1QEbDHgnc", "formats": [{"uri": "ipfs://QmY7p9UeGZeVUWRAfCQJm5nvQFHTNyfTWEPsH9Qympbkf1", "mimeType": "image/png"}], "creators": ["tz1ZGSztGWzwdmVMEqfe7bFWdS2sjxZggS9a"], "tags": ["liveexperience", "beets", "hereandnow", "liveevent", "interactive"], "extra": {}}