{"__version":1,"extra":{"display_uris":[]},"token_id":95467,"symbol":"OBJKT","creators":["tz1UCD8FNcVNPhzRk8ExAkd5PuwFmu5ey1JP"],"name":"Uruguayada","description":"En este gif, todo es reconocible por casi cualquier uruguayo. El ojo de Sauron por supuesto escapa a la idea, pero me pareció divertido.","tags":["Uruguay","OmarGurierrez","Suarez","DanielMartínez","Gaucho","gif","digital","collage"],"formats":[{"mimeType":"image/gif","uri":"ipfs://QmctQ26pGDhF2sgH7YsqEuj9zfvkUR3nCZ4HJkonfUguEr"}],"artifact_uri":"ipfs://QmctQ26pGDhF2sgH7YsqEuj9zfvkUR3nCZ4HJkonfUguEr","display_uri":"","thumbnail_uri":"ipfs://QmNrhZHUaEqxhyLfqoq1mtHSipkWHeT31LNHb1QEbDHgnc"}