{"__version":1,"extra":{"display_uris":[]},"token_id":57175,"symbol":"OBJKT","creators":["tz1WzQh4yDUuTpZBDdRwMrnkV9bs1upnSANF"],"name":"Calm 8bit Window (Include original 8bit Music)","description":"8bit animation on peaceful 8 bit music. Dedicated to John Karel the 01/05/20121.","tags":["Animation","8bit","Sega","Music","Hicetnunc","8bitmusic","window",""],"formats":[{"mimeType":"video/mp4","uri":"ipfs://QmUiqbcV8iaKU69Cz814cL4JYuXqZM3DhCGgKQLBqwtQUk"}],"artifact_uri":"ipfs://QmUiqbcV8iaKU69Cz814cL4JYuXqZM3DhCGgKQLBqwtQUk","display_uri":"","thumbnail_uri":"ipfs://QmNrhZHUaEqxhyLfqoq1mtHSipkWHeT31LNHb1QEbDHgnc"}