{"__version":1,"extra":{"display_uris":[]},"token_id":73423,"symbol":"OBJKT","creators":["tz1iD7LwGyJMtUQ7pRB5Rb4y1jXTTBYf8PWV"],"name":"\"The Mystery Unfolds\" by Richard F. Yates (Holy Fool)","description":"[Felt pens on paper with digital embellishments and color, and with some help from my almost two-year-old granddaughter, Felicity!] The ghosts and spirits gather and swirl about the room... Must be movie night! ---Richard F. Yates (Holy Fool)","tags":["art","digitalart","drawings","handdrawn","feltpenonpaper","ghosts","spirits","nfts"],"formats":[{"mimeType":"image/png","uri":"ipfs://QmedP9TMt5me3wqXsVVUyTzVW5sb2JNAU48snrFwStBomN"}],"artifact_uri":"ipfs://QmedP9TMt5me3wqXsVVUyTzVW5sb2JNAU48snrFwStBomN","display_uri":"","thumbnail_uri":"ipfs://QmNrhZHUaEqxhyLfqoq1mtHSipkWHeT31LNHb1QEbDHgnc"}