{"__version":1,"extra":{"display_uris":[]},"token_id":59261,"symbol":"OBJKT","creators":["tz1Yfw9jYJbayzmAD6bx29yPs8jskLEaVFe6"],"name":"Beautiful Romantic Flag Painting_#000","description":"@DZ015_ *Experiments on abstraction, haiku, gesture and temporality","tags":["abstract","painting","flag","double","repetitive","action","screencapture","haiku","gesture","emoji","abstracted","smudge","shor"],"formats":[{"mimeType":"video/quicktime","uri":"ipfs://QmQwH4veitRBTG5hCVNUW1UPhkK8f3WSGNaWjJUyYC3szU"}],"artifact_uri":"ipfs://QmQwH4veitRBTG5hCVNUW1UPhkK8f3WSGNaWjJUyYC3szU","display_uri":"","thumbnail_uri":"ipfs://QmNrhZHUaEqxhyLfqoq1mtHSipkWHeT31LNHb1QEbDHgnc"}