{"__version": 1, "token_id": 133894, "symbol": "OBJKT", "name": "OK.Computer - S01 - GPU", "description": "OK Computer - A project that reminds me of my childhood and that technology is always evolving and growing with me. In this collectible series you can collect the PC that gave us huge opportunities to dive in world of internet, gaming and creativity. Every person, who collects all items will receive a full PC package NFT as well as an NFT of collecting process as a bonus to my collectors.", "artifact_uri": "ipfs://QmNjjhMkRP7uSCzK3N6BWBMxSe5oy5m4FfPiV5TtKw8r22", "display_uri": "ipfs://QmQbUpEi5erKvkNnZvjuiwDXMBJjKQAsabz6rm5qMhoPV2", "thumbnail_uri": "ipfs://QmNrhZHUaEqxhyLfqoq1mtHSipkWHeT31LNHb1QEbDHgnc", "formats": [{"uri": "ipfs://QmNjjhMkRP7uSCzK3N6BWBMxSe5oy5m4FfPiV5TtKw8r22", "mimeType": "video/mp4"}], "creators": ["tz1UGKRjpaLX8SZNAi7Sy2Aa1JwyFPX826ys"], "tags": ["90s", "AMD", "INTEL", "CUTE", "NVIDIA", "APPLE", "COLLECTIBLE", "COMMODORE64", "GAME", "OKCOMPUTER", "RETROWAVE", "ZXSPECTRUM", "CREAMTOYS", "PC"], "extra": {}}