{"__version": 1, "token_id": 196505, "symbol": "OBJKT", "name": "MSRI Double Sided 3", "description": "v4w.enko - \"MSRI Double Sided 3\" This is generative audio visual fragment generated with custom definition.  \"Three energies are in deep ballance to bring the harmony in slow stream\".  Colors are open and connected to the sound.  The sound is interactive with the transformations. \n", "artifact_uri": "ipfs://QmYYorRbtBoV7BQCrmxaxQYm1swjPnsxLFyNFrZFC548gU", "display_uri": "ipfs://QmSg9aH3GezvhoCYAhbicNsPziB3Sb3K2gopjGeQEAJnJh", "thumbnail_uri": "ipfs://QmNrhZHUaEqxhyLfqoq1mtHSipkWHeT31LNHb1QEbDHgnc", "formats": [{"uri": "ipfs://QmYYorRbtBoV7BQCrmxaxQYm1swjPnsxLFyNFrZFC548gU", "mimeType": "video/mp4"}], "creators": ["tz1Mpr7WD3UG47UFPbizLPnBCNhh8pcdbSyz"], "tags": ["generative", "realtime", "abstraction", "open", "colors", "raw", "sound", "digitalart", "audiovisual", "parametric", "v4wenko", "orange", "green", "blue."], "extra": {}}