{"__version":1,"extra":{"display_uris":[]},"token_id":63141,"symbol":"OBJKT","creators":["tz29LqGEjCrSR1HFhzMoujZvXi5Rgdhxe7mP"],"name":"Trying 2 Fit In","description":"A workout photo with equipment hanging and flipped upside down to showcase how, at times, people kill themselves and turn their world upside down just 2 fit in.","tags":["Health","help","crowd","live","life"],"formats":[{"mimeType":"image/jpeg","uri":"ipfs://QmVBvfqfgSK2ffbRNdCodjmVp2KpK7p8NJKeATDPDsK958"}],"artifact_uri":"ipfs://QmVBvfqfgSK2ffbRNdCodjmVp2KpK7p8NJKeATDPDsK958","display_uri":"","thumbnail_uri":"ipfs://QmNrhZHUaEqxhyLfqoq1mtHSipkWHeT31LNHb1QEbDHgnc"}