{"contract":"KT1RJ6PbjHpwc3M5rw5s2Nbmefwbuwbdxton","network":"mainnet","level":1422134,"token_id":27958,"symbol":"OBJKT","name":"CAUTION WIDE LOADING III","decimals":0,"description":"Typographic tribute to VIDEONICS 'Video Titlemaker' series and every other horribly interfaced, slow-loading, ancient piece of technology out there on the road... Part of @cali4niaclub's bumper sticker group show: https://cali4nia.club","artifact_uri":"ipfs://QmW5o2W3d6fdFMocS1HuUG4TfQsSbzGJuCJziTyzc4fKKY","thumbnail_uri":"ipfs://QmNrhZHUaEqxhyLfqoq1mtHSipkWHeT31LNHb1QEbDHgnc","formats":[{"mimeType":"image/gif","uri":"ipfs://QmW5o2W3d6fdFMocS1HuUG4TfQsSbzGJuCJziTyzc4fKKY"}],"token_info":{"@@empty":"ipfs://QmbFAdnFeLdwwe8MATJakYNkh8ZRFBEGgU2vVrSFoETFCS"},"supply":"50","transfered":54}