{"__version":1,"extra":{"display_uris":[{"mimeType":"image/jpeg","file":"48219-128.jpeg","fileSize":1113,"dimensions":{"value":"128x85","unit":"px"},"path":"QmPVjyXgg7ZEH3pZ3zK6w9krMouCjSdcwB74k3zWpgFKbH","cid":"QmPVjyXgg7ZEH3pZ3zK6w9krMouCjSdcwB74k3zWpgFKbH"},{"mimeType":"image/jpeg","file":"48219-512.jpeg","fileSize":8164,"dimensions":{"value":"512x341","unit":"px"},"path":"QmW1SJeHMxGxGvHMKRFzAKnp7ZAVDZ48FFtanwb3Kpg9kV","cid":"QmW1SJeHMxGxGvHMKRFzAKnp7ZAVDZ48FFtanwb3Kpg9kV"},{"mimeType":"image/jpeg","file":"48219-1024.jpeg","fileSize":28473,"dimensions":{"value":"1024x683","unit":"px"},"path":"QmUTjKPhPUQeXDF9wkCojQpr9L5LRg3AKtGY6PcMQDJfSM","cid":"QmUTjKPhPUQeXDF9wkCojQpr9L5LRg3AKtGY6PcMQDJfSM"}]},"token_id":48219,"symbol":"OBJKT","creators":["tz1aLNfjoXRu3p6QwRhi6dZpmdrsRHG2pXPc"],"name":"Merman Art for Burning man 2021","description":"The virtual world meets reality. The real art object that got a grant from Burning Man in 2021 was created by a group of artists who bring art to Nevada since 2015. A huge statue of a human, made of wood and metal floating in the desert. Merman's mission is to remind people that no matter how hard the times are, life is worth staying afloat. We choose not to surrender to the turbulent stream of life. Want to support us? Check other pieces. merman.worlak.com, instagram.com/merman_art","tags":["mermanart","burningman","defaultworld","BRC","blackrockcity","Loverock","burningman2021","burningmanvideos","burningman2021","burningman","swimmer","desert","visualisation","realart","wooden","wood","landscape","sculpture","realart","physicalart","OBJKT4OBJKT"],"formats":[{"mimeType":"image/png","uri":"ipfs://QmchKqZdhQjyfYmUsLcBvz6QZtm2umimkqfeAzibrGnuZz"}],"artifact_uri":"ipfs://QmchKqZdhQjyfYmUsLcBvz6QZtm2umimkqfeAzibrGnuZz","display_uri":"ipfs://QmUTjKPhPUQeXDF9wkCojQpr9L5LRg3AKtGY6PcMQDJfSM","thumbnail_uri":"ipfs://QmNrhZHUaEqxhyLfqoq1mtHSipkWHeT31LNHb1QEbDHgnc"}