{"contract": "KT1RJ6PbjHpwc3M5rw5s2Nbmefwbuwbdxton", "network": "mainnet", "level": 1482060, "token_id": 92664, "symbol": "OBJKT", "name": "Addicted...", "decimals": 0, "description": "we all have different addiction refer to us we have a lot of addiction", "artifact_uri": "ipfs://Qmagg7NpndS1o2x8dDTb5zznFxV89zM3YfRfvJ8gpDA9Kx", "thumbnail_uri": "ipfs://QmNrhZHUaEqxhyLfqoq1mtHSipkWHeT31LNHb1QEbDHgnc", "is_transferable": true, "creators": ["tz1icwXWQjLTqxXjapLXLFbMNsDCYTRbD56F"], "tags": ["cinema4d", "octane", "octanerender", "aftereffects", "videocopilot", "element3d", "trippy", "trippyartwork", "trippyartwork", "psychedelic", "psychedelicart", "psychedelicartwork", "psychedelicartist", "crypto", "cryptoart", "cryptoartist", "cryptoartwork", "nft", "nftart", "nftartist", "nftcollector", "nftcommunity", "psychonaut", "spaceart", "scifi", "scifiart", "astro", "astronaut"], "formats": [{"mimeType": "image/jpeg", "uri": "ipfs://Qmagg7NpndS1o2x8dDTb5zznFxV89zM3YfRfvJ8gpDA9Kx"}], "token_info": {"@@empty": "ipfs://QmW6ju47XYRFjpAVw3UafV2fGph5pVhpaH1KXt5Are55mi"}, "supply": "10", "transfered": 10}