{"__version":1,"extra":{"display_uris":[]},"token_id":126639,"symbol":"OBJKT","creators":["tz1ammKuzWPxL3hYkHFT6ebTxGnfn4RfCb2X"],"name":"O Lago.","description":"Essa é uma animação que fiz em \"30 DE DEZEMBRO DE 2020\" para meu instagram pessoal. @SebastianBevilaqua - Está disponível como contribuição ao evento #oBRjkt, um evento para fortalecer a comunidade Brasileira no HEN. Artist: Sebastian Bevilaqua | 1000x1000 - 60Fps Sound Off.","tags":["nft","hen","oBRjkt","3dart","3danimation"],"formats":[{"uri":"ipfs://QmSdL1baKR3tW19T1p8ucTewrHf7q4PpTXmdx1R9JTi6x9","mimeType":"video/mp4"}],"artifact_uri":"ipfs://QmSdL1baKR3tW19T1p8ucTewrHf7q4PpTXmdx1R9JTi6x9","display_uri":"ipfs://Qmcgfq1qAjtWLyhwiawXjuJpWva6hV4TEanrRNLTAdvq2i","thumbnail_uri":"ipfs://QmNrhZHUaEqxhyLfqoq1mtHSipkWHeT31LNHb1QEbDHgnc"}