{"__version": 1, "token_id": 194239, "symbol": "OBJKT", "name": "Upper Tree of Life 19", "description": "Part 19 of a 28 minute video (each part in a series of 11), these parts can be joined together to make the full 28 minute video (1440p,60fps). Upper Tree of Life is a Virtual Reality interpretation of an acrylic painting study on the Kabbalah Tree of Life. Called the Upper Tree of Life, this is the divine version of the Kabbalah Tree. Video capture of a VR painting using Tilt Brush and Open Brush, original music by Barry Chabala (barrychabala.bandcamp.com/   IG: @barry.chabala.roeba.recordings   Twitter: @BarryChabala). The remaining parts of the video will be released in the upcoming days/weeks.", "artifact_uri": "ipfs://QmWAmEeA3D3AEz8nnZYRFVrAYeHjENJauDa2JYeccseEBw", "display_uri": "ipfs://QmWcY1FX6xRrYT9o9Sb9x8nXpFyqQ9VkZ6DmJStaHCZXiR", "thumbnail_uri": "ipfs://QmNrhZHUaEqxhyLfqoq1mtHSipkWHeT31LNHb1QEbDHgnc", "formats": [{"uri": "ipfs://QmWAmEeA3D3AEz8nnZYRFVrAYeHjENJauDa2JYeccseEBw", "mimeType": "video/mp4"}], "creators": ["tz1StkowNLzbtGuJFKhAR1urdrEGNwsbgLuM"], "tags": ["VR", "Visual", "OriginalMusic", "SacredGeometry", "Digital", "OpenBrush", "VRPainting", "Kabbalah"], "extra": {}}