{"__version":1,"extra":{"display_uris":[]},"token_id":78927,"symbol":"OBJKT","creators":["tz1dsQwLuckYoyH8uWegqixKgZ7TCwHbFeFf"],"name":"Faceless Crypto 7","description":"Faceless Crypto 7 (2719x4272px) This art is a project of digital collage using only a static image with abstract elements created in photoshop","tags":["digitalart","abstract","surrealism","photoshop","colors","digitalcollage",""],"formats":[{"mimeType":"image/png","uri":"ipfs://Qmdp2n48QVehKX73UgbbHMbYVAgKbYbC5iBV9RRd6Mj16X"}],"artifact_uri":"ipfs://Qmdp2n48QVehKX73UgbbHMbYVAgKbYbC5iBV9RRd6Mj16X","display_uri":"","thumbnail_uri":"ipfs://QmNrhZHUaEqxhyLfqoq1mtHSipkWHeT31LNHb1QEbDHgnc"}