{"name": "Orbital Terminus", "description": "Figure 00X1 in the COSMIC-ANATOMY series. \"The brain is the organ of destiny. It holds within its humming mechanism secrets that will determine the future of the human race.\" -Wilder Penfield", "tags": ["art", "digitalart", "abstract", "cosmic-anatomy", "space"], "symbol": "OBJKT", "artifactUri": "ipfs://QmRNY4xJh1Ub3NwGDpWXyRRiRv9e24D3YmWJ3peLK1FaiL", "displayUri": "ipfs://QmPZDarrEU8qVVFVigh1Ju39jFHAycGXoxntZPoCPY3qnt", "thumbnailUri": "ipfs://QmNrhZHUaEqxhyLfqoq1mtHSipkWHeT31LNHb1QEbDHgnc", "creators": ["tz1cvJgvRpLrzACgaxZ8shGioY7LRMUez3RC"], "formats": [{"uri": "ipfs://QmRNY4xJh1Ub3NwGDpWXyRRiRv9e24D3YmWJ3peLK1FaiL", "mimeType": "image/jpeg"}], "decimals": 0, "isBooleanAmount": false, "shouldPreferSymbol": false}